{
  "v005": {
    "label": "online_safe",
    "relative_root": ".",
    "deep_binary": "code/deep/v005/dual-deep-v6",
    "fast_binary": "code/fast/v005/dual-fast-v19"
  },
  "v006": {
    "label": "online_slope",
    "relative_root": ".",
    "deep_binary": "code/deep/v006/dual-deep-v6",
    "fast_binary": "code/fast/v006/dual-fast-v19"
  },
  "v007": {
    "label": "bandit",
    "relative_root": ".",
    "deep_binary": "code/deep/v007/dual-deep-v6",
    "fast_binary": "code/fast/v007/dual-fast-v19"
  },
  "v009": {
    "label": "tuned_bandit",
    "relative_root": ".",
    "deep_binary": "code/deep/v009/dual-deep-v6",
    "fast_binary": "code/fast/v009/dual-fast-v19"
  }
}
